foxcolor/__init__.py
foxcolor-1.0.0.dist-info/METADATA
foxcolor-1.0.0.dist-info/WHEEL
foxcolor-1.0.0.dist-info/top_level.txt
foxcolor-1.0.0.dist-info/RECORD
