Metadata-Version: 2.1
Name: foxcolor
Version: 1.0.0
Summary: Biblioteca de cores para o python, com uma vasta variedades de cores para serem usadas.
Home-page: https://github.com/FoxWaynne/FoxColor/
Author: @FoxWaynne
Author-email: foxys.fow@gmail.com
Requires-Dist: argparse
Requires-Dist: colorama
